{
  "started": 1561935600,
  "ended": 1567292880,
  "timestep": 60,
  "telescope": "⌀0.5m",
  "neos_scanned": 52,
  "exoplanets_scanned": 77,
  "max_slew_rate": 0.73,
  "operations": [
    {
      "type": 2,
      "begin": 1561935660,
      "end": 1561947060,
      "data": {
        "nid": "a0068031",
        "spkid": 2068031,
        "designation": 68031,
        "name": "",
        "full_name": "68031 2000 YK29",
        "integration_time": 11338,
        "mag": 18.1,
        "vmag": 18.209,
        "pha": 0,
        "smass": "",
        "tholen": "",
        "slew_max": 0.02
      }
    },
    {
      "type": 2,
      "begin": 1561947360,
      "end": 1561947900,
      "data": {
        "nid": "a0214088",
        "spkid": 2214088,
        "designation": 214088,
        "name": "",
        "full_name": "214088 2004 JN13",
        "integration_time": 499,
        "mag": 15.3,
        "vmag": 14.815,
        "pha": 0,
        "smass": "",
        "tholen": "",
        "slew_max": 0.04
      }
    },
    {
      "type": 2,
      "begin": 1561948200,
      "end": 1561958340,
      "data": {
        "nid": "a0455736",
        "spkid": 2455736,
        "designation": 455736,
        "name": "",
        "full_name": "455736 2005 HC3",
        "integration_time": 10193,
        "mag": 17.8,
        "vmag": 18.094,
        "pha": 0,
        "smass": "",
        "tholen": "",
        "slew_max": 0.04
      }
    },
    {
      "type": 2,
      "begin": 1561958640,
      "end": 1561975440,
      "data": {
        "nid": "a0467317",
        "spkid": 2467317,
        "designation": 467317,
        "name": "",
        "full_name": "467317 2000 QW7",
        "integration_time": 16628,
        "mag": 19.8,
        "vmag": 18.626,
        "pha": 1,
        "smass": "",
        "tholen": "",
        "slew_max": 0.01
      }
    },
    {
      "type": 2,
      "begin": 1561975740,
      "end": 1561982580,
      "data": {
        "nid": "bK08O02V",
        "spkid": 3421944,
        "designation": "2008 OV2",
        "name": "",
        "full_name": "2008 OV2",
        "integration_time": 6812,
        "mag": 20.3,
        "vmag": 17.656,
        "pha": 0,
        "smass": "",
        "tholen": "",
        "slew_max": 0.08
      }
    },
    {
      "type": 2,
      "begin": 1561982880,
      "end": 1561997880,
      "data": {
        "nid": "bK09O03B",
        "spkid": 3464766,
        "designation": "2009 OB3",
        "name": "",
        "full_name": "2009 OB3",
        "integration_time": 14899,
        "mag": 18.9,
        "vmag": 18.506,
        "pha": 0,
        "smass": "",
        "tholen": "",
        "slew_max": 0.04
      }
    },
    {
      "type": 2,
      "begin": 1561998180,
      "end": 1562007300,
      "data": {
        "nid": "bK11H00T",
        "spkid": 3563860,
        "designation": "2011 HT",
        "name": "",
        "full_name": "2011 HT",
        "integration_time": 9102,
        "mag": 21.9,
        "vmag": 17.971,
        "pha": 0,
        "smass": "",
        "tholen": "",
        "slew_max": 0.11
      }
    },
    {
      "type": 2,
      "begin": 1562007600,
      "end": 1562027040,
      "data": {
        "nid": "bK11T04C",
        "spkid": 3581507,
        "designation": "2011 TC4",
        "name": "",
        "full_name": "2011 TC4",
        "integration_time": 19941,
        "mag": 20.3,
        "vmag": 18.823,
        "pha": 1,
        "smass": "",
        "tholen": "",
        "slew_max": 0.04
      }
    },
    {
      "type": 1,
      "begin": 1562027340,
      "end": 1562027400,
      "data": {
        "name": "KELT-10 b",
        "host": "KELT-10",
        "period": 359966,
        "transit_duration": 13487,
        "optmag": 10.854,
        "spect_num": 1
      }
    },
    {
      "type": 2,
      "begin": 1562027700,
      "end": 1562040960,
      "data": {
        "nid": "bK19B05J",
        "spkid": 3838216,
        "designation": "2019 BJ5",
        "name": "",
        "full_name": "2019 BJ5",
        "integration_time": 13245,
        "mag": 18.185,
        "vmag": 18.378,
        "pha": 0,
        "smass": "",
        "tholen": "",
        "slew_max": 0.03
      }
    },
    {
      "type": 1,
      "begin": 1562043420,
      "end": 1562043480,
      "data": {
        "name": "HATS-65 b",
        "host": "HATS-65",
        "period": 268286,
        "transit_duration": 10403,
        "optmag": 12.497,
        "spect_num": 1
      }
    },
    {
      "type": 1,
      "begin": 1562048340,
      "end": 1562048580,
      "data": {
        "name": "HATS-11 b",
        "host": "HATS-11",
        "period": 312698,
        "transit_duration": 15509,
        "optmag": 14.018,
        "spect_num": 1
      }
    },
    {
      "type": 2,
      "begin": 1562054040,
      "end": 1562060640,
      "data": {
        "nid": "bK08L16W",
        "spkid": 3414251,
        "designation": "2008 LW16",
        "name": "",
        "full_name": "2008 LW16",
        "integration_time": 6597,
        "mag": 19.8,
        "vmag": 17.621,
        "pha": 1,
        "smass": "",
        "tholen": "",
        "slew_max": 0.11
      }
    },
    {
      "type": 1,
      "begin": 1562082240,
      "end": 1562082600,
      "data": {
        "name": "HATS-36 b",
        "host": "HATS-36",
        "period": 360736,
        "transit_duration": 12321,
        "optmag": 14.386,
        "spect_num": 1
      }
    },
    {
      "type": 1,
      "begin": 1562101620,
      "end": 1562101680,
      "data": {
        "name": "WASP-123 b",
        "host": "WASP-123",
        "period": 257268,
        "transit_duration": 11128,
        "optmag": 11.1,
        "spect_num": 1
      }
    },
    {
      "type": 1,
      "begin": 1562111100,
      "end": 1562111220,
      "data": {
        "name": "HATS-10 b",
        "host": "HATS-10",
        "period": 286230,
        "transit_duration": 10791,
        "optmag": 13.113,
        "spect_num": 1
      }
    },
    {
      "type": 1,
      "begin": 1562129340,
      "end": 1562129520,
      "data": {
        "name": "HATS-9 b",
        "host": "HATS-9",
        "period": 165481,
        "transit_duration": 13245,
        "optmag": 13.276,
        "spect_num": 1
      }
    },
    {
      "type": 2,
      "begin": 1562151840,
      "end": 1562155200,
      "data": {
        "nid": "a0154229",
        "spkid": 2154229,
        "designation": 154229,
        "name": "",
        "full_name": "154229 2002 JN97",
        "integration_time": 3339,
        "mag": 16.5,
        "vmag": 16.881,
        "pha": 0,
        "smass": "",
        "tholen": "",
        "slew_max": 0.03
      }
    },
    {
      "type": 1,
      "begin": 1562167800,
      "end": 1562167920,
      "data": {
        "name": "CoRoT-2 b",
        "host": "CoRoT-2",
        "period": 150595,
        "transit_duration": 8346,
        "optmag": 12.57,
        "spect_num": 1
      }
    },
    {
      "type": 1,
      "begin": 1562176200,
      "end": 1562176740,
      "data": {
        "name": "CoRoT-8 b",
        "host": "CoRoT-8",
        "period": 536742,
        "transit_duration": 9314,
        "optmag": 14.8,
        "spect_num": 1
      }
    },
    {
      "type": 1,
      "begin": 1562179020,
      "end": 1562179320,
      "data": {
        "name": "HATS-8 b",
        "host": "HATS-8",
        "period": 309648,
        "transit_duration": 10956,
        "optmag": 14.03,
        "spect_num": 1
      }
    },
    {
      "type": 1,
      "begin": 1562205120,
      "end": 1562205180,
      "data": {
        "name": "WASP-80 b",
        "host": "WASP-80",
        "period": 265062,
        "transit_duration": 7785,
        "optmag": 11.87,
        "spect_num": 1
      }
    },
    {
      "type": 1,
      "begin": 1562212200,
      "end": 1562213160,
      "data": {
        "name": "CoRoT-17 b",
        "host": "CoRoT-17",
        "period": 325564,
        "transit_duration": 17556,
        "optmag": 15.46,
        "spect_num": 1
      }
    },
    {
      "type": 1,
      "begin": 1562226420,
      "end": 1562226540,
      "data": {
        "name": "HATS-12 b",
        "host": "HATS-12",
        "period": 271529,
        "transit_duration": 10368,
        "optmag": 12.756,
        "spect_num": 1
      }
    },
    {
      "type": 1,
      "begin": 1562252640,
      "end": 1562253420,
      "data": {
        "name": "CoRoT-10 b",
        "host": "CoRoT-10",
        "period": 1143988,
        "transit_duration": 9383,
        "optmag": 15.22,
        "spect_num": 1
      }
    },
    {
      "type": 1,
      "begin": 1562345340,
      "end": 1562345640,
      "data": {
        "name": "HATS-50 b",
        "host": "HATS-50",
        "period": 330886,
        "transit_duration": 11120,
        "optmag": 14.033,
        "spect_num": 1
      }
    },
    {
      "type": 1,
      "begin": 1562362980,
      "end": 1562364060,
      "data": {
        "name": "CoRoT-16 b",
        "host": "CoRoT-16",
        "period": 462436,
        "transit_duration": 9616,
        "optmag": 15.63,
        "spect_num": 1
      }
    },
    {
      "type": 1,
      "begin": 1562400600,
      "end": 1562400720,
      "data": {
        "name": "WASP-133 b",
        "host": "WASP-133",
        "period": 188043,
        "transit_duration": 12502,
        "optmag": 12.9,
        "spect_num": 1
      }
    },
    {
      "type": 1,
      "begin": 1562426220,
      "end": 1562426760,
      "data": {
        "name": "HATS-15 b",
        "host": "HATS-15",
        "period": 150983,
        "transit_duration": 8217,
        "optmag": 14.774,
        "spect_num": 1
      }
    },
    {
      "type": 1,
      "begin": 1562438160,
      "end": 1562438220,
      "data": {
        "name": "HATS-3 b",
        "host": "HATS-3",
        "period": 306534,
        "transit_duration": 12917,
        "optmag": 12.44,
        "spect_num": 1
      }
    },
    {
      "type": 2,
      "begin": 1562446500,
      "end": 1562465460,
      "data": {
        "nid": "a0468540",
        "spkid": 2468540,
        "designation": 468540,
        "name": "",
        "full_name": "468540 2006 MD12",
        "integration_time": 18640,
        "mag": 19.4,
        "vmag": 18.75,
        "pha": 0,
        "smass": "",
        "tholen": "",
        "slew_max": 0.05
      }
    },
    {
      "type": 1,
      "begin": 1562490180,
      "end": 1562490420,
      "data": {
        "name": "HATS-14 b",
        "host": "HATS-14",
        "period": 239048,
        "transit_duration": 9521,
        "optmag": 13.79,
        "spect_num": 1
      }
    },
    {
      "type": 1,
      "begin": 1562496600,
      "end": 1562496840,
      "data": {
        "name": "HATS-62 b",
        "host": "HATS-62",
        "period": 283123,
        "transit_duration": 9953,
        "optmag": 14.015,
        "spect_num": 1
      }
    },
    {
      "type": 2,
      "begin": 1562506560,
      "end": 1562511300,
      "data": {
        "nid": "a0153842",
        "spkid": 2153842,
        "designation": 153842,
        "name": "",
        "full_name": "153842 2001 XT30",
        "integration_time": 4671,
        "mag": 16.7,
        "vmag": 17.246,
        "pha": 0,
        "smass": "",
        "tholen": "",
        "slew_max": 0.01
      }
    },
    {
      "type": 2,
      "begin": 1562535360,
      "end": 1562547240,
      "data": {
        "nid": "bK05N21E",
        "spkid": 3283679,
        "designation": "2005 NE21",
        "name": "",
        "full_name": "2005 NE21",
        "integration_time": 11740,
        "mag": 21.2,
        "vmag": 18.247,
        "pha": 0,
        "smass": "",
        "tholen": "",
        "slew_max": 0.1
      }
    },
    {
      "type": 2,
      "begin": 1562547540,
      "end": 1562552280,
      "data": {
        "nid": "bK16AD0U",
        "spkid": 3739672,
        "designation": "2016 AU130",
        "name": "",
        "full_name": "2016 AU130",
        "integration_time": 4712,
        "mag": 18.5,
        "vmag": 17.255,
        "pha": 0,
        "smass": "",
        "tholen": "",
        "slew_max": 0.07
      }
    },
    {
      "type": 1,
      "begin": 1562668080,
      "end": 1562668200,
      "data": {
        "name": "WASP-89 b",
        "host": "WASP-89",
        "period": 289995,
        "transit_duration": 9910,
        "optmag": 13.1,
        "spect_num": 1
      }
    },
    {
      "type": 2,
      "begin": 1562701800,
      "end": 1562723400,
      "data": {
        "nid": "a0499986",
        "spkid": 2499986,
        "designation": 499986,
        "name": "",
        "full_name": "499986 2011 NP",
        "integration_time": 21197,
        "mag": 20,
        "vmag": 18.889,
        "pha": 0,
        "smass": "",
        "tholen": "",
        "slew_max": 0.08
      }
    },
    {
      "type": 1,
      "begin": 1562760660,
      "end": 1562760900,
      "data": {
        "name": "HATS-13 b",
        "host": "HATS-13",
        "period": 263006,
        "transit_duration": 9521,
        "optmag": 13.887,
        "spect_num": 1
      }
    },
    {
      "type": 2,
      "begin": 1562809500,
      "end": 1562831100,
      "data": {
        "nid": "bK06O15H",
        "spkid": 3337835,
        "designation": "2006 OH15",
        "name": "",
        "full_name": "2006 OH15",
        "integration_time": 21392,
        "mag": 18.9,
        "vmag": 18.899,
        "pha": 0,
        "smass": "",
        "tholen": "",
        "slew_max": 0.05
      }
    },
    {
      "type": 1,
      "begin": 1562881380,
      "end": 1562881500,
      "data": {
        "name": "K2-231 b",
        "host": "K2-231",
        "period": 1195940,
        "transit_duration": 10584,
        "optmag": 12.708,
        "spect_num": 1
      }
    },
    {
      "type": 1,
      "begin": 1562883540,
      "end": 1562883660,
      "data": {
        "name": "K2-107 b",
        "host": "K2-107",
        "period": 286326,
        "transit_duration": 12770,
        "optmag": 12.92,
        "spect_num": 1
      }
    },
    {
      "type": 1,
      "begin": 1562945400,
      "end": 1562945460,
      "data": {
        "name": "WASP-70 A b",
        "host": "WASP-70 A",
        "period": 320805,
        "transit_duration": 12096,
        "optmag": 10.79,
        "spect_num": 1
      }
    },
    {
      "type": 2,
      "begin": 1563182040,
      "end": 1563200820,
      "data": {
        "nid": "a0143678",
        "spkid": 2143678,
        "designation": 143678,
        "name": "",
        "full_name": "143678 2003 SA224",
        "integration_time": 18779,
        "mag": 16.3,
        "vmag": 18.758,
        "pha": 0,
        "smass": "",
        "tholen": "",
        "slew_max": 0.01
      }
    },
    {
      "type": 2,
      "begin": 1563201120,
      "end": 1563222480,
      "data": {
        "nid": "a0438661",
        "spkid": 2438661,
        "designation": 438661,
        "name": "",
        "full_name": "438661 2008 EP6",
        "integration_time": 20980,
        "mag": 19.4,
        "vmag": 18.878,
        "pha": 1,
        "smass": "",
        "tholen": "",
        "slew_max": 0.03
      }
    },
    {
      "type": 2,
      "begin": 1563305760,
      "end": 1563327360,
      "data": {
        "nid": "bK13N11T",
        "spkid": 3645001,
        "designation": "2013 NT11",
        "name": "",
        "full_name": "2013 NT11",
        "integration_time": 21380,
        "mag": 19.6,
        "vmag": 18.899,
        "pha": 0,
        "smass": "",
        "tholen": "",
        "slew_max": 0.09
      }
    },
    {
      "type": 1,
      "begin": 1563459960,
      "end": 1563460020,
      "data": {
        "name": "WASP-90 b",
        "host": "WASP-90",
        "period": 338363,
        "transit_duration": 12113,
        "optmag": 11.7,
        "spect_num": 1
      }
    },
    {
      "type": 2,
      "begin": 1563519900,
      "end": 1563541500,
      "data": {
        "nid": "a0052750",
        "spkid": 2052750,
        "designation": 52750,
        "name": "",
        "full_name": "52750 1998 KK17",
        "integration_time": 21429,
        "mag": 16.4,
        "vmag": 18.901,
        "pha": 0,
        "smass": "",
        "tholen": "",
        "slew_max": 0.02
      }
    },
    {
      "type": 2,
      "begin": 1563541800,
      "end": 1563542580,
      "data": {
        "nid": "a0455432",
        "spkid": 2455432,
        "designation": 455432,
        "name": "",
        "full_name": "455432 2003 RP8",
        "integration_time": 763,
        "mag": 18.2,
        "vmag": 15.276,
        "pha": 0,
        "smass": "",
        "tholen": "",
        "slew_max": 0.14
      }
    },
    {
      "type": 2,
      "begin": 1563710100,
      "end": 1563724320,
      "data": {
        "nid": "a0381677",
        "spkid": 2381677,
        "designation": 381677,
        "name": "",
        "full_name": "381677 2009 BJ81",
        "integration_time": 14321,
        "mag": 18.3,
        "vmag": 18.463,
        "pha": 0,
        "smass": "",
        "tholen": "",
        "slew_max": 0.01
      }
    },
    {
      "type": 2,
      "begin": 1563771720,
      "end": 1563784020,
      "data": {
        "nid": "a0354030",
        "spkid": 2354030,
        "designation": 354030,
        "name": "",
        "full_name": "354030 2001 RB18",
        "integration_time": 12161,
        "mag": 18.5,
        "vmag": 18.286,
        "pha": 0,
        "smass": "",
        "tholen": "",
        "slew_max": 0.01
      }
    },
    {
      "type": 1,
      "begin": 1563868740,
      "end": 1563868860,
      "data": {
        "name": "WASP-124 b",
        "host": "WASP-124",
        "period": 291397,
        "transit_duration": 9279,
        "optmag": 12.7,
        "spect_num": 1
      }
    },
    {
      "type": 1,
      "begin": 1563881100,
      "end": 1563881160,
      "data": {
        "name": "K2-139 b",
        "host": "K2-139",
        "period": 2452085,
        "transit_duration": 19233,
        "optmag": 11.653,
        "spect_num": 1
      }
    },
    {
      "type": 2,
      "begin": 1563904380,
      "end": 1563914700,
      "data": {
        "nid": "a0007482",
        "spkid": 2007482,
        "designation": 7482,
        "name": "",
        "full_name": "7482 1994 PC1",
        "integration_time": 10267,
        "mag": 16.8,
        "vmag": 18.102,
        "pha": 1,
        "smass": "S",
        "tholen": "",
        "slew_max": 0.03
      }
    },
    {
      "type": 2,
      "begin": 1563915000,
      "end": 1563936540,
      "data": {
        "nid": "bK08S82J",
        "spkid": 3427986,
        "designation": "2008 SJ82",
        "name": "",
        "full_name": "2008 SJ82",
        "integration_time": 21250,
        "mag": 20.7,
        "vmag": 18.892,
        "pha": 1,
        "smass": "",
        "tholen": "",
        "slew_max": 0.02
      }
    },
    {
      "type": 2,
      "begin": 1563964200,
      "end": 1563972360,
      "data": {
        "nid": "bK15H10M",
        "spkid": 3717042,
        "designation": "2015 HM10",
        "name": "",
        "full_name": "2015 HM10",
        "integration_time": 8070,
        "mag": 23.6,
        "vmag": 17.84,
        "pha": 0,
        "smass": "",
        "tholen": "",
        "slew_max": 0.34
      }
    },
    {
      "type": 2,
      "begin": 1564063260,
      "end": 1564074060,
      "data": {
        "nid": "a0089355",
        "spkid": 2089355,
        "designation": 89355,
        "name": "",
        "full_name": "89355 2001 VS78",
        "integration_time": 10743,
        "mag": 15.6,
        "vmag": 18.151,
        "pha": 0,
        "smass": "S",
        "tholen": "",
        "slew_max": 0.02
      }
    },
    {
      "type": 2,
      "begin": 1564145460,
      "end": 1564151880,
      "data": {
        "nid": "a0002059",
        "spkid": 2002059,
        "designation": 2059,
        "name": "Baboquivari",
        "full_name": "2059 Baboquivari 1963 UA",
        "integration_time": 6365,
        "mag": 15.9,
        "vmag": 17.582,
        "pha": 0,
        "smass": "",
        "tholen": "",
        "slew_max": 0.01
      }
    },
    {
      "type": 2,
      "begin": 1564159080,
      "end": 1564160160,
      "data": {
        "nid": "bK10P09K",
        "spkid": 3542519,
        "designation": "2010 PK9",
        "name": "",
        "full_name": "2010 PK9",
        "integration_time": 1052,
        "mag": 21.8,
        "vmag": 15.626,
        "pha": 1,
        "smass": "",
        "tholen": "",
        "slew_max": 0.73
      }
    },
    {
      "type": 1,
      "begin": 1564259640,
      "end": 1564259700,
      "data": {
        "name": "WASP-47 e",
        "host": "WASP-47",
        "period": 68221,
        "transit_duration": 6836,
        "optmag": 11.9,
        "spect_num": 1
      }
    },
    {
      "type": 1,
      "begin": 1564306140,
      "end": 1564306320,
      "data": {
        "name": "K2-55 b",
        "host": "K2-55",
        "period": 246176,
        "transit_duration": 7222,
        "optmag": 13.546,
        "spect_num": 1
      }
    },
    {
      "type": 2,
      "begin": 1564347060,
      "end": 1564358760,
      "data": {
        "nid": "a0429733",
        "spkid": 2429733,
        "designation": 429733,
        "name": "",
        "full_name": "429733 2011 LX10",
        "integration_time": 11678,
        "mag": 16.6,
        "vmag": 18.242,
        "pha": 0,
        "smass": "",
        "tholen": "",
        "slew_max": 0.02
      }
    },
    {
      "type": 2,
      "begin": 1564402260,
      "end": 1564405560,
      "data": {
        "nid": "a0293054",
        "spkid": 2293054,
        "designation": 293054,
        "name": "",
        "full_name": "293054 2006 WP127",
        "integration_time": 3301,
        "mag": 18.3,
        "vmag": 16.868,
        "pha": 0,
        "smass": "",
        "tholen": "",
        "slew_max": 0.05
      }
    },
    {
      "type": 1,
      "begin": 1564464420,
      "end": 1564464480,
      "data": {
        "name": "K2-58 c",
        "host": "K2-58",
        "period": 219219,
        "transit_duration": 7186,
        "optmag": 12.378,
        "spect_num": 1
      }
    },
    {
      "type": 2,
      "begin": 1564609680,
      "end": 1564612560,
      "data": {
        "nid": "a0054509",
        "spkid": 2054509,
        "designation": 54509,
        "name": "YORP",
        "full_name": "54509 YORP 2000 PH5",
        "integration_time": 2892,
        "mag": 22.7,
        "vmag": 16.725,
        "pha": 0,
        "smass": "",
        "tholen": "",
        "slew_max": 0.1
      }
    },
    {
      "type": 1,
      "begin": 1564669980,
      "end": 1564670280,
      "data": {
        "name": "K2-64 b",
        "host": "K2-64",
        "period": 564230,
        "transit_duration": 11016,
        "optmag": 14.086,
        "spect_num": 1
      }
    },
    {
      "type": 1,
      "begin": 1564692420,
      "end": 1564692480,
      "data": {
        "name": "K2-62 b",
        "host": "K2-62",
        "period": 576463,
        "transit_duration": 5076,
        "optmag": 12.397,
        "spect_num": 1
      }
    },
    {
      "type": 2,
      "begin": 1564724820,
      "end": 1564746420,
      "data": {
        "nid": "a0434786",
        "spkid": 2434786,
        "designation": 434786,
        "name": "",
        "full_name": "434786 2006 PW",
        "integration_time": 21199,
        "mag": 18.1,
        "vmag": 18.89,
        "pha": 0,
        "smass": "",
        "tholen": "",
        "slew_max": 0.03
      }
    },
    {
      "type": 1,
      "begin": 1564753980,
      "end": 1564754100,
      "data": {
        "name": "WASP-114 b",
        "host": "WASP-114",
        "period": 133814,
        "transit_duration": 9996,
        "optmag": 12.743,
        "spect_num": 1
      }
    },
    {
      "type": 1,
      "begin": 1564763520,
      "end": 1564765140,
      "data": {
        "name": "K2-28 b",
        "host": "K2-28",
        "period": 195303,
        "transit_duration": 3966,
        "optmag": 16.061,
        "spect_num": 1
      }
    },
    {
      "type": 2,
      "begin": 1564824900,
      "end": 1564846500,
      "data": {
        "nid": "a0458732",
        "spkid": 2458732,
        "designation": 458732,
        "name": "",
        "full_name": "458732 2011 MD5",
        "integration_time": 21550,
        "mag": 17.9,
        "vmag": 18.907,
        "pha": 0,
        "smass": "",
        "tholen": "",
        "slew_max": 0.02
      }
    },
    {
      "type": 1,
      "begin": 1564882500,
      "end": 1564882620,
      "data": {
        "name": "K2-60 b",
        "host": "K2-60",
        "period": 259429,
        "transit_duration": 9988,
        "optmag": 12.789,
        "spect_num": 1
      }
    },
    {
      "type": 1,
      "begin": 1564901940,
      "end": 1564902480,
      "data": {
        "name": "K2-69 b",
        "host": "K2-69",
        "period": 610502,
        "transit_duration": 5832,
        "optmag": 14.807,
        "spect_num": 1
      }
    },
    {
      "type": 2,
      "begin": 1564909860,
      "end": 1564914360,
      "data": {
        "nid": "bK17S17R",
        "spkid": 3781910,
        "designation": "2017 SR17",
        "name": "",
        "full_name": "2017 SR17",
        "integration_time": 4452,
        "mag": 18.8,
        "vmag": 17.193,
        "pha": 0,
        "smass": "",
        "tholen": "",
        "slew_max": 0
      }
    },
    {
      "type": 1,
      "begin": 1564930740,
      "end": 1564930860,
      "data": {
        "name": "K2-280 b",
        "host": "K2-280",
        "period": 1718945,
        "transit_duration": 20892,
        "optmag": 12.536,
        "spect_num": 1
      }
    },
    {
      "type": 1,
      "begin": 1564980780,
      "end": 1564980840,
      "data": {
        "name": "K2-58 b",
        "host": "K2-58",
        "period": 609339,
        "transit_duration": 6836,
        "optmag": 12.378,
        "spect_num": 1
      }
    },
    {
      "type": 1,
      "begin": 1565055900,
      "end": 1565055960,
      "data": {
        "name": "K2-265 b",
        "host": "K2-265",
        "period": 204696,
        "transit_duration": 8571,
        "optmag": 11.102,
        "spect_num": 1
      }
    },
    {
      "type": 1,
      "begin": 1565088480,
      "end": 1565088600,
      "data": {
        "name": "K2-61 b",
        "host": "K2-61",
        "period": 222309,
        "transit_duration": 8388,
        "optmag": 12.991,
        "spect_num": 1
      }
    },
    {
      "type": 1,
      "begin": 1565132700,
      "end": 1565132820,
      "data": {
        "name": "K2-75 b",
        "host": "K2-75",
        "period": 675147,
        "transit_duration": 19728,
        "optmag": 12.701,
        "spect_num": 1
      }
    },
    {
      "type": 1,
      "begin": 1565165580,
      "end": 1565165700,
      "data": {
        "name": "HATS-60 b",
        "host": "HATS-60",
        "period": 307656,
        "transit_duration": 13928,
        "optmag": 12.641,
        "spect_num": 1
      }
    },
    {
      "type": 1,
      "begin": 1565229120,
      "end": 1565229420,
      "data": {
        "name": "K2-59 c",
        "host": "K2-59",
        "period": 975923,
        "transit_duration": 6300,
        "optmag": 14.226,
        "spect_num": 1
      }
    },
    {
      "type": 1,
      "begin": 1565246820,
      "end": 1565246940,
      "data": {
        "name": "K2-70 b",
        "host": "K2-70",
        "period": 1207782,
        "transit_duration": 12672,
        "optmag": 12.989,
        "spect_num": 1
      }
    },
    {
      "type": 1,
      "begin": 1565270100,
      "end": 1565270160,
      "data": {
        "name": "K2-73 b",
        "host": "K2-73",
        "period": 647605,
        "transit_duration": 13032,
        "optmag": 11.345,
        "spect_num": 1
      }
    },
    {
      "type": 1,
      "begin": 1565275920,
      "end": 1565275980,
      "data": {
        "name": "WASP-75 b",
        "host": "WASP-75",
        "period": 214634,
        "transit_duration": 7102,
        "optmag": 11.45,
        "spect_num": 1
      }
    },
    {
      "type": 1,
      "begin": 1565304420,
      "end": 1565304840,
      "data": {
        "name": "K2-57 b",
        "host": "K2-57",
        "period": 778144,
        "transit_duration": 8244,
        "optmag": 14.501,
        "spect_num": 1
      }
    },
    {
      "type": 1,
      "begin": 1565321280,
      "end": 1565321640,
      "data": {
        "name": "HATS-32 b",
        "host": "HATS-32",
        "period": 243013,
        "transit_duration": 10282,
        "optmag": 14.384,
        "spect_num": 1
      }
    },
    {
      "type": 1,
      "begin": 1565341200,
      "end": 1565341500,
      "data": {
        "name": "K2-54 b",
        "host": "K2-54",
        "period": 845364,
        "transit_duration": 9936,
        "optmag": 14.042,
        "spect_num": 1
      }
    },
    {
      "type": 1,
      "begin": 1565418060,
      "end": 1565418600,
      "data": {
        "name": "K2-71 b",
        "host": "K2-71",
        "period": 603539,
        "transit_duration": 5076,
        "optmag": 14.875,
        "spect_num": 1
      }
    },
    {
      "type": 1,
      "begin": 1565428800,
      "end": 1565428920,
      "data": {
        "name": "K2-68 b",
        "host": "K2-68",
        "period": 695890,
        "transit_duration": 9792,
        "optmag": 12.977,
        "spect_num": 1
      }
    },
    {
      "type": 2,
      "begin": 1565440860,
      "end": 1565452440,
      "data": {
        "nid": "bK17T01C",
        "spkid": 3782059,
        "designation": "2017 TC1",
        "name": "",
        "full_name": "2017 TC1",
        "integration_time": 11570,
        "mag": 20.9,
        "vmag": 18.231,
        "pha": 0,
        "smass": "",
        "tholen": "",
        "slew_max": 0
      }
    },
    {
      "type": 1,
      "begin": 1565465940,
      "end": 1565466000,
      "data": {
        "name": "K2-65 b",
        "host": "K2-65",
        "period": 1092744,
        "transit_duration": 12348,
        "optmag": 10.801,
        "spect_num": 1
      }
    },
    {
      "type": 1,
      "begin": 1565642040,
      "end": 1565642100,
      "data": {
        "name": "K2-62 c",
        "host": "K2-62",
        "period": 1399386,
        "transit_duration": 4644,
        "optmag": 12.397,
        "spect_num": 1
      }
    },
    {
      "type": 2,
      "begin": 1565698020,
      "end": 1565716620,
      "data": {
        "nid": "bK06P01F",
        "spkid": 3337999,
        "designation": "2006 PF1",
        "name": "",
        "full_name": "2006 PF1",
        "integration_time": 18057,
        "mag": 19.5,
        "vmag": 18.715,
        "pha": 0,
        "smass": "",
        "tholen": "",
        "slew_max": 0.05
      }
    },
    {
      "type": 1,
      "begin": 1565768160,
      "end": 1565768220,
      "data": {
        "name": "K2-138 b",
        "host": "K2-138",
        "period": 203318,
        "transit_duration": 6791,
        "optmag": 12.21,
        "spect_num": 1
      }
    },
    {
      "type": 1,
      "begin": 1565829060,
      "end": 1565829120,
      "data": {
        "name": "K2-138 d",
        "host": "K2-138",
        "period": 466973,
        "transit_duration": 9245,
        "optmag": 12.21,
        "spect_num": 1
      }
    },
    {
      "type": 2,
      "begin": 1565868060,
      "end": 1565870700,
      "data": {
        "nid": "a0005786",
        "spkid": 2005786,
        "designation": 5786,
        "name": "Talos",
        "full_name": "5786 Talos 1991 RC",
        "integration_time": 2621,
        "mag": 17.1,
        "vmag": 16.617,
        "pha": 0,
        "smass": "",
        "tholen": "",
        "slew_max": 0.08
      }
    },
    {
      "type": 1,
      "begin": 1565898420,
      "end": 1565898540,
      "data": {
        "name": "K2-63 b",
        "host": "K2-63",
        "period": 1750205,
        "transit_duration": 19764,
        "optmag": 12.876,
        "spect_num": 1
      }
    },
    {
      "type": 1,
      "begin": 1565963700,
      "end": 1565963760,
      "data": {
        "name": "K2-138 c",
        "host": "K2-138",
        "period": 307573,
        "transit_duration": 8035,
        "optmag": 12.21,
        "spect_num": 1
      }
    },
    {
      "type": 2,
      "begin": 1565971080,
      "end": 1565989380,
      "data": {
        "nid": "bK16P01D",
        "spkid": 3756911,
        "designation": "2016 PD1",
        "name": "",
        "full_name": "2016 PD1",
        "integration_time": 17785,
        "mag": 23.7,
        "vmag": 18.699,
        "pha": 0,
        "smass": "",
        "tholen": "",
        "slew_max": 0.11
      }
    },
    {
      "type": 1,
      "begin": 1566113640,
      "end": 1566113760,
      "data": {
        "name": "K2-75 c",
        "host": "K2-75",
        "period": 1582070,
        "transit_duration": 23112,
        "optmag": 12.701,
        "spect_num": 1
      }
    },
    {
      "type": 1,
      "begin": 1566147420,
      "end": 1566147480,
      "data": {
        "name": "K2-58 d",
        "host": "K2-58",
        "period": 1977065,
        "transit_duration": 11520,
        "optmag": 12.378,
        "spect_num": 1
      }
    },
    {
      "type": 2,
      "begin": 1566191940,
      "end": 1566213540,
      "data": {
        "nid": "a0163760",
        "spkid": 2163760,
        "designation": 163760,
        "name": "",
        "full_name": "163760 2003 OR14",
        "integration_time": 21496,
        "mag": 16.6,
        "vmag": 18.905,
        "pha": 0,
        "smass": "",
        "tholen": "",
        "slew_max": 0.01
      }
    },
    {
      "type": 1,
      "begin": 1566234900,
      "end": 1566234960,
      "data": {
        "name": "K2-285 c",
        "host": "K2-285",
        "period": 616727,
        "transit_duration": 9107,
        "optmag": 12.03,
        "spect_num": 1
      }
    },
    {
      "type": 1,
      "begin": 1566248640,
      "end": 1566248700,
      "data": {
        "name": "K2-285 b",
        "host": "K2-285",
        "period": 299959,
        "transit_duration": 7897,
        "optmag": 12.03,
        "spect_num": 1
      }
    },
    {
      "type": 1,
      "begin": 1566249720,
      "end": 1566249780,
      "data": {
        "name": "K2-138 e",
        "host": "K2-138",
        "period": 713788,
        "transit_duration": 10912,
        "optmag": 12.21,
        "spect_num": 1
      }
    },
    {
      "type": 2,
      "begin": 1566258300,
      "end": 1566279900,
      "data": {
        "nid": "bK06Q23S",
        "spkid": 3338369,
        "designation": "2006 QS23",
        "name": "",
        "full_name": "2006 QS23",
        "integration_time": 21008,
        "mag": 20.1,
        "vmag": 18.88,
        "pha": 0,
        "smass": "",
        "tholen": "",
        "slew_max": 0.04
      }
    },
    {
      "type": 2,
      "begin": 1566312060,
      "end": 1566325380,
      "data": {
        "nid": "bK16P66X",
        "spkid": 3757565,
        "designation": "2016 PX66",
        "name": "",
        "full_name": "2016 PX66",
        "integration_time": 13278,
        "mag": 18.6,
        "vmag": 18.381,
        "pha": 0,
        "smass": "",
        "tholen": "",
        "slew_max": 0.04
      }
    },
    {
      "type": 1,
      "begin": 1566377220,
      "end": 1566377280,
      "data": {
        "name": "GJ 9827 b",
        "host": "GJ 9827",
        "period": 104456,
        "transit_duration": 4501,
        "optmag": 10.25,
        "spect_num": 1
      }
    },
    {
      "type": 1,
      "begin": 1566430680,
      "end": 1566430740,
      "data": {
        "name": "WASP-52 b",
        "host": "WASP-52",
        "period": 151181,
        "transit_duration": 6523,
        "optmag": 12,
        "spect_num": 1
      }
    },
    {
      "type": 1,
      "begin": 1566431880,
      "end": 1566431940,
      "data": {
        "name": "K2-285 d",
        "host": "K2-285",
        "period": 903383,
        "transit_duration": 9055,
        "optmag": 12.03,
        "spect_num": 1
      }
    },
    {
      "type": 2,
      "begin": 1566458940,
      "end": 1566480540,
      "data": {
        "nid": "bK13C89K",
        "spkid": 3626730,
        "designation": "2013 CK89",
        "name": "",
        "full_name": "2013 CK89",
        "integration_time": 21294,
        "mag": 18,
        "vmag": 18.894,
        "pha": 0,
        "smass": "",
        "tholen": "",
        "slew_max": 0.01
      }
    },
    {
      "type": 2,
      "begin": 1566505440,
      "end": 1566512760,
      "data": {
        "nid": "bK15J11F",
        "spkid": 3720880,
        "designation": "2015 JF11",
        "name": "",
        "full_name": "2015 JF11",
        "integration_time": 7252,
        "mag": 20.8,
        "vmag": 17.724,
        "pha": 0,
        "smass": "",
        "tholen": "",
        "slew_max": 0.05
      }
    },
    {
      "type": 2,
      "begin": 1566562680,
      "end": 1566584280,
      "data": {
        "nid": "bK06D00Y",
        "spkid": 3323935,
        "designation": "2006 DY",
        "name": "",
        "full_name": "2006 DY",
        "integration_time": 21391,
        "mag": 18.4,
        "vmag": 18.899,
        "pha": 0,
        "smass": "",
        "tholen": "",
        "slew_max": 0.02
      }
    },
    {
      "type": 1,
      "begin": 1566615360,
      "end": 1566615420,
      "data": {
        "name": "WASP-28 b",
        "host": "WASP-28",
        "period": 294523,
        "transit_duration": 11673,
        "optmag": 12.03,
        "spect_num": 1
      }
    },
    {
      "type": 1,
      "begin": 1566626700,
      "end": 1566626820,
      "data": {
        "name": "K2-74 b",
        "host": "K2-74",
        "period": 1690554,
        "transit_duration": 18432,
        "optmag": 12.588,
        "spect_num": 1
      }
    },
    {
      "type": 1,
      "begin": 1566634740,
      "end": 1566634800,
      "data": {
        "name": "GJ 9827 c",
        "host": "GJ 9827",
        "period": 315194,
        "transit_duration": 6540,
        "optmag": 10.25,
        "spect_num": 1
      }
    },
    {
      "type": 1,
      "begin": 1566662040,
      "end": 1566662160,
      "data": {
        "name": "WASP-151 b",
        "host": "WASP-151",
        "period": 391692,
        "transit_duration": 13176,
        "optmag": 12.795,
        "spect_num": 1
      }
    },
    {
      "type": 1,
      "begin": 1566714360,
      "end": 1566714420,
      "data": {
        "name": "GJ 9827 d",
        "host": "GJ 9827",
        "period": 535807,
        "transit_duration": 4398,
        "optmag": 10.25,
        "spect_num": 1
      }
    },
    {
      "type": 1,
      "begin": 1566727860,
      "end": 1566727920,
      "data": {
        "name": "K2-138 f",
        "host": "K2-138",
        "period": 1102256,
        "transit_duration": 12269,
        "optmag": 12.21,
        "spect_num": 1
      }
    },
    {
      "type": 2,
      "begin": 1566786180,
      "end": 1566788760,
      "data": {
        "nid": "a0152754",
        "spkid": 2152754,
        "designation": 152754,
        "name": "",
        "full_name": "152754 1999 GS6",
        "integration_time": 2578,
        "mag": 19.1,
        "vmag": 16.6,
        "pha": 1,
        "smass": "",
        "tholen": "",
        "slew_max": 0.06
      }
    },
    {
      "type": 2,
      "begin": 1566795480,
      "end": 1566809220,
      "data": {
        "nid": "a0424089",
        "spkid": 2424089,
        "designation": 424089,
        "name": "",
        "full_name": "424089 2007 DU103",
        "integration_time": 13720,
        "mag": 17.7,
        "vmag": 18.417,
        "pha": 0,
        "smass": "",
        "tholen": "",
        "slew_max": 0.03
      }
    },
    {
      "type": 1,
      "begin": 1566827640,
      "end": 1566827700,
      "data": {
        "name": "WASP-136 b",
        "host": "WASP-136",
        "period": 450607,
        "transit_duration": 19829,
        "optmag": 9.98,
        "spect_num": 1
      }
    },
    {
      "type": 2,
      "begin": 1566908220,
      "end": 1566918900,
      "data": {
        "nid": "bK01R17W",
        "spkid": 3092326,
        "designation": "2001 RW17",
        "name": "",
        "full_name": "2001 RW17",
        "integration_time": 10711,
        "mag": 19.7,
        "vmag": 18.148,
        "pha": 0,
        "smass": "",
        "tholen": "",
        "slew_max": 0.04
      }
    },
    {
      "type": 2,
      "begin": 1566921420,
      "end": 1566931140,
      "data": {
        "nid": "a0405212",
        "spkid": 2405212,
        "designation": 405212,
        "name": "",
        "full_name": "405212 2003 QC10",
        "integration_time": 9606,
        "mag": 18,
        "vmag": 18.029,
        "pha": 1,
        "smass": "",
        "tholen": "",
        "slew_max": 0.02
      }
    },
    {
      "type": 1,
      "begin": 1566941340,
      "end": 1566941460,
      "data": {
        "name": "WASP-44 b",
        "host": "WASP-44",
        "period": 209417,
        "transit_duration": 8087,
        "optmag": 12.9,
        "spect_num": 1
      }
    },
    {
      "type": 1,
      "begin": 1566986340,
      "end": 1566986400,
      "data": {
        "name": "WASP-20 b",
        "host": "WASP-20",
        "period": 423328,
        "transit_duration": 12269,
        "optmag": 10.68,
        "spect_num": 1
      }
    },
    {
      "type": 1,
      "begin": 1566987240,
      "end": 1566987300,
      "data": {
        "name": "WASP-21 b",
        "host": "WASP-21",
        "period": 373462,
        "transit_duration": 13029,
        "optmag": 11.58,
        "spect_num": 1
      }
    },
    {
      "type": 2,
      "begin": 1567200060,
      "end": 1567221660,
      "data": {
        "nid": "a0108906",
        "spkid": 2108906,
        "designation": 108906,
        "name": "",
        "full_name": "108906 2001 PL9",
        "integration_time": 21368,
        "mag": 17.8,
        "vmag": 18.898,
        "pha": 0,
        "smass": "",
        "tholen": "",
        "slew_max": 0.02
      }
    },
    {
      "type": 2,
      "begin": 1567226760,
      "end": 1567248360,
      "data": {
        "nid": "a0006047",
        "spkid": 2006047,
        "designation": 6047,
        "name": "",
        "full_name": "6047 1991 TB1",
        "integration_time": 21368,
        "mag": 17.8,
        "vmag": 18.898,
        "pha": 0,
        "smass": "S",
        "tholen": "",
        "slew_max": 0.02
      }
    }
  ],
  "earth_exclusion": 10,
  "exoplanet_spectroscopy_limiting": "not limited",
  "neo_spectroscopy_limiting": "360 minutes integration time",
  "exoplanet_avg_scan_time": 162,
  "neo_avg_scan_time": 12744,
  "time_exoplanet_scans": "0.3",
  "time_neo_scans": "12.5",
  "time_idle": "87.2",
  "total_data_produced_tb": 1.35,
  "data_rate_mbps": 2,
  "data_rate_fluct_mbps": 0.1,
  "exoplanet_count": 2629,
  "neo_count": 19782,
  "ecliptic_scope": "50°x50°",
  "neo_spectroscopy_methodology": "scan once",
  "exoplanet_spectroscopy_methodology": "scan once"
}